cinemat/__init__.py
cinemat/__main__.py
cinemat/config.py
cinemat/get_details.py
cinemat/help.py
cinemat/restful_events.py
cinemat/search.py
cinemator-0.1.4.dist-info/METADATA
cinemator-0.1.4.dist-info/WHEEL
cinemator-0.1.4.dist-info/dependency_links.txt
cinemator-0.1.4.dist-info/entry_points.txt
cinemator-0.1.4.dist-info/top_level.txt
cinemator-0.1.4.dist-info/RECORD
