Metadata-Version: 2.1
Name: cinemator
Version: 0.1.4
Summary: Command Line Tool to dig into movies at OMDBAPI
Home-page: https://github.com/helixphoenix/cinemator
Author: helixphoenix
Author-email: helixphoenix@gmail.com
Maintainer: helixphoenix
Platform: any
Classifier: Development Status :: 4 - Beta
Classifier: Programming Language :: Python
Requires-Python: >=3
